{
  "kind": "collectionType",
  "collectionName": "models",
  "info": {
    "singularName": "model",
    "pluralName": "models",
    "displayName": "Model"
  },
  "options": {
    "draftAndPublish": true
  },
  "pluginOptions": {},
  "attributes": {
    "module_id": {
      "type": "uid"
    },
    "title": {
      "type": "string"
    },
    "file": {
      "type": "media",
      "multiple": false,
      "required": true,
      "allowedTypes": [
        "files"
      ]
    },
    "metadata": {
      "type": "json"
    },
    "coworking_space": {
      "type": "relation",
      "relation": "manyToOne",
      "target": "api::coworking-space.coworking-space",
      "inversedBy": "models"
    }
  }
}